{
  "project_info": {
    "project_number": "803738012168",
    "project_id": "hiqruweb",
    "storage_bucket": "hiqruweb.appspot.com"
  },
  "client": [
    {
      "client_info": {
        "mobilesdk_app_id": "1:803738012168:android:2e988d1c9b185a87cfdfbd",
        "android_client_info": {
          "package_name": "com.lcargo.mobile"
        }
      },
      "oauth_client": [
        {
          "client_id": "803738012168-jnjnrdefprcnkl7kstibi6l1di1a4smn.apps.googleusercontent.com",
          "client_type": 3
        }
      ],
      "api_key": [
        {
          "current_key": "AIzaSyCCb7aJozFIQMsxr3WOsuDRt5aoAKGLmJ4"
        }
      ],
      "services": {
        "appinvite_service": {
          "other_platform_oauth_client": [
            {
              "client_id": "803738012168-jnjnrdefprcnkl7kstibi6l1di1a4smn.apps.googleusercontent.com",
              "client_type": 3
            }
          ]
        }
      }
    }
  ],
  "configuration_version": "1"
}